japick/__init__.py
japick/cleaner.py
japick/lines.py
japick/main.py
japick/paragraph.py
japick/parser.py
japick/syntax.py
japick-0.6.2.dist-info/METADATA
japick-0.6.2.dist-info/WHEEL
japick-0.6.2.dist-info/top_level.txt
japick-0.6.2.dist-info/RECORD
