Metadata-Version: 2.1
Name: japick
Version: 0.6.2
Summary: UNKNOWN
Home-page: https://shodo.ink/
Author: ZenProducts Inc.
Author-email: info@shodo.ink
License: UNKNOWN
Platform: UNKNOWN
Provides-Extra: tests
Requires-Dist: black ; extra == 'tests'
Requires-Dist: invoke ; extra == 'tests'
Requires-Dist: isort ; extra == 'tests'
Requires-Dist: pytest ; extra == 'tests'
